agrivoltaics_supply_side_management/__init__.py
agrivoltaics_supply_side_management/configuration.py
agrivoltaics_supply_side_management/agriculture/__init__.py
agrivoltaics_supply_side_management/agriculture/crops.py
agrivoltaics_supply_side_management/agriculture/photosynthesis.py
agrivoltaics_supply_side_management/agriculture/photosynthetic_rate.py
agrivoltaics_supply_side_management/optimization/__init__.py
agrivoltaics_supply_side_management/optimization/convex_optimization.py
agrivoltaics_supply_side_management/photovoltaics/__init__.py
agrivoltaics_supply_side_management/photovoltaics/pv_modules.py
agrivoltaics_supply_side_management/solar_irradiation/__init__.py
agrivoltaics_supply_side_management/solar_irradiation/clearsky.py
agrivoltaics_supply_side_management/solar_irradiation/irradiance.py
agrivoltaics_supply_side_management/supply/__init__.py
agrivoltaics_supply_side_management/supply/strategy.py
agrivoltaics_supply_side_management/supply/strategy_factory.py
agrivoltaics_supply_side_management/tests/__init__.py
agrivoltaics_supply_side_management/tests/test_configuration.py
agrivoltaics_supply_side_management/tests/agriculture/__init__.py
agrivoltaics_supply_side_management/tests/agriculture/test_crops.py
agrivoltaics_supply_side_management/tests/agriculture/test_photosynthesis.py
agrivoltaics_supply_side_management/tests/agriculture/test_photosynthetic_rate.py
agrivoltaics_supply_side_management/tests/optimization/__init__.py
agrivoltaics_supply_side_management/tests/optimization/test_convex_optimization.py
agrivoltaics_supply_side_management/tests/photovoltaics/__init__.py
agrivoltaics_supply_side_management/tests/photovoltaics/test_pv_modules.py
agrivoltaics_supply_side_management/tests/solar_irradiation/__init__.py
agrivoltaics_supply_side_management/tests/solar_irradiation/test_clearsky.py
agrivoltaics_supply_side_management/tests/supply/__init__.py
agrivoltaics_supply_side_management/tests/supply/test_strategy.py
agrivoltaics_supply_side_management-0.1.0.dist-info/LICENSE.txt
agrivoltaics_supply_side_management-0.1.0.dist-info/METADATA
agrivoltaics_supply_side_management-0.1.0.dist-info/WHEEL
agrivoltaics_supply_side_management-0.1.0.dist-info/top_level.txt
agrivoltaics_supply_side_management-0.1.0.dist-info/RECORD
