Metadata-Version: 2.1
Name: agrivoltaics-supply-side-management
Version: 0.1.0
Summary: Optimizes Supply Side Management with Agrivoltaics by Artificial Intelligence
Home-page: UNKNOWN
Author: Tadatoshi Takahashi
Author-email: tadatoshi@gmail.com
License: UNKNOWN
Keywords: agrivoltaics,time series analysis,bayesian modeling,data analysis,development
Platform: UNKNOWN
Classifier: Development Status :: 3 - Alpha
Classifier: Intended Audience :: Developers
Classifier: License :: OSI Approved :: MIT License
Classifier: Programming Language :: Python :: 3
Classifier: Programming Language :: Python :: 3.6
Classifier: Programming Language :: Python :: 3.7
Classifier: Programming Language :: Python :: 3.8
Classifier: Programming Language :: Python :: 3.9
Classifier: Programming Language :: Python :: 3.10
Classifier: Programming Language :: Python :: 3 :: Only
Requires-Python: >=3.6, <4
License-File: LICENSE.txt
Requires-Dist: numpy
Requires-Dist: pandas
Requires-Dist: matplotlib
Requires-Dist: seaborn
Requires-Dist: scikit-learn
Requires-Dist: statsmodels
Requires-Dist: tensorflow
Requires-Dist: tensorflow-probability
Requires-Dist: pymc3
Requires-Dist: pvlib
Requires-Dist: opencv-python
Requires-Dist: pyomo
Requires-Dist: kneed
Requires-Dist: jupyterlab
Provides-Extra: test
Requires-Dist: pytest ; extra == 'test'
Requires-Dist: hypothesis ; extra == 'test'
Requires-Dist: click ; extra == 'test'
Requires-Dist: black ; extra == 'test'
